ewatercycle_experiment_launcher/__init__.py
ewatercycle_experiment_launcher/auth.py
ewatercycle_experiment_launcher/generate.py
ewatercycle_experiment_launcher/hub.py
ewatercycle_experiment_launcher/openapi.yaml
ewatercycle_experiment_launcher/process.py
ewatercycle_experiment_launcher/serve.py
ewatercycle_experiment_launcher/swagger.yaml
ewatercycle_experiment_launcher/api/__init__.py
ewatercycle_experiment_launcher/api/bmi.py
ewatercycle_experiment_launcher/api/hello.py
ewatercycle_experiment_launcher/api/opendap.py
ewatercycle_experiment_launcher/api/threeclickscience.py
ewatercycle_experiment_launcher-0.2.0.dist-info/LICENSE
ewatercycle_experiment_launcher-0.2.0.dist-info/METADATA
ewatercycle_experiment_launcher-0.2.0.dist-info/WHEEL
ewatercycle_experiment_launcher-0.2.0.dist-info/top_level.txt
ewatercycle_experiment_launcher-0.2.0.dist-info/RECORD
