Metadata-Version: 2.1
Name: ewatercycle-experiment-launcher
Version: 0.2.0
Summary: Webservice to generate and launch a Jupyter notebook
Home-page: https://github.com/ewatercycle/ewatercycle_experiment_launcher
Author: Stefan Verhoeven
Author-email: s.verhoeven@esciencecenter.nl
License: Apache Software License 2.0
Keywords: ewatercycle_experiment_launcher
Platform: UNKNOWN
Classifier: Development Status :: 2 - Pre-Alpha
Classifier: Intended Audience :: Developers
Classifier: License :: OSI Approved :: Apache Software License
Classifier: Natural Language :: English
Classifier: Programming Language :: Python :: 3
Classifier: Programming Language :: Python :: 3.5
Classifier: Programming Language :: Python :: 3.6
Requires-Dist: nbformat
Requires-Dist: requests
Requires-Dist: connexion[swagger-ui]
Requires-Dist: connexion
Requires-Dist: gunicorn
Requires-Dist: decorator
Requires-Dist: simplepam
Requires-Dist: flask-cors
Requires-Dist: jsonschema (==2.6.0)
